verilogcodes/verilogcodes/full_adder1/full_adder.v
//Behavioral Modeling
/*module full_adder(
    input a,
    input b,
    input cin,
    output reg sum,
    output reg carry
);
always @(a,b,cin)
begin
    if(a==0 && b==0 && cin==0)begin
        sum=0; carry=0;
    end
    else if(a==0 && b==0 && cin==1)begin
        sum=1; carry=0;
    end
    else if(a==0 && b==1 && cin==0)begin
        sum=1; carry=0;
    end
    else if(a==0 && b==1 && cin==1)begin
        sum=0; carry=1;
    end
    else if(a==1 && b==0 && cin==0)begin
        sum=1; carry=0;
    end
    else if(a==1 && b==0 && cin==1)begin
        sum=0; carry=1;
    end
    else if(a==1 && b==1 && cin==0)begin
        sum=0; carry=1;
    end
    else if(a==1 && b==1 && cin==1)begin
        sum=1; carry=1;
    end

end
endmodule*/

//Gate-Level Modeling
/*module half_adderforfull(
    input a,
    input b,
    output sum,
    output carry
);

assign sum=a^b;
assign carry=a&b;
endmodule

module full_adder(
    input A,
    input B,
    input Cin,
    output Sum,
    output Carry
);
wire w1,w2,w3;
half_adderforfull f1(.a(A),.b(B),.sum(w1),.carry(w2));
half_adderforfull f2(.a(w1),.b(Cin),.sum(Sum),.carry(w3));
or f3(Carry,w3,w3);
endmodule*/

//Dataflow Modeling
module full_adder(
    input A,B,Cin,
    output Sum,Carry
);

assign Sum=A^B^Cin;
assign Carry=(A&B) | (Cin&(A^B));

endmodule

verilogcodes/4 bit adder/full_adder_tb.v
`timescale 1ns/1ps
module full_adder_tb;
reg A,B,Cin;
wire Sum;
wire Carry;
full_adder uut(
    .A(A),
    .B(B),
    .Cin(Cin),
    .Sum(Sum),
    .Carry(Carry)
);

initial begin
    A=0; B=0; Cin=0; #10
    A=0; B=0; Cin=1; #10
    A=0; B=1; Cin=0; #10
    A=0; B=1; Cin=1; #10
    A=1; B=0; Cin=0; #10
    A=1; B=0; Cin=1; #10
    A=1; B=1; Cin=0; #10
    A=1; B=1; Cin=1; #10
    $finish;
end

initial begin
    $dumpfile("full_adder.vcd");
    $dumpvars();
end
endmodule

verilogcodes/4 bit adder/full_adder.vcd
$date
	Mon Mar 30 12:39:03 2026
$end
$version
	Icarus Verilog
$end
$timescale
	1ps
$end
$scope module full_adder_tb $end
$var wire 1 ! Sum $end
$var wire 1 " Carry $end
$var reg 1 # A $end
$var reg 1 $ B $end
$var reg 1 % Cin $end
$scope module uut $end
$var wire 1 # A $end
$var wire 1 $ B $end
$var wire 1 " Carry $end
$var wire 1 % Cin $end
$var wire 1 ! Sum $end
$upscope $end
$upscope $end
$enddefinitions $end
$comment Show the parameter values. $end
$dumpall
$end
#0
$dumpvars
0%
0$
0#
0"
0!
$end
#10000
1!
1%
#20000
0%
1$
#30000
1"
0!
1%
#40000
0"
1!
0%
0$
1#
#50000
1"
0!
1%
#60000
0%
1$
#70000
1!
1%
