verilogcodes/counters/updowncounter/updowncount.v
//Behavioral Modeling
// 3-bit UP-Down Counter

module updowncount(
    input clk,
    input reset,
    input ud,
    output reg [2:0] count

);

always @ (posedge clk or posedge reset)
begin
    if (reset)
    count <= 3'b000;
    else if (ud)
        count<=count+1;
    else
        count<=count-1;
end
endmodule

verilogcodes/counters/updowncounter/updowncounttb.v
`timescale 1ns/1ps
module updowncounttb;

reg clk, ud, reset;
wire [2:0] count;

updowncount uut(
    .clk(clk),
    .reset(reset),
    .count(count),
    .ud(ud)
);

initial begin
    clk=0;
    forever #5 clk=~clk;
end

initial begin
    reset=1; ud=1;
    #10 reset=0;

    ud=1;
    #50
    ud=0;
    #50

    reset=1; 
    #10 reset=0;

    ud=1;
    #50
    $finish;
end

initial begin
    $dumpfile("updowncount.vcd");
    $dumpvars(0,updowncounttb);

end

endmodule

verilogcodes/counters/updowncounter/updowncount.vcd
$date
	Thu Apr 16 14:22:18 2026
$end
$version
	Icarus Verilog
$end
$timescale
	1ps
$end
$scope module updowncounttb $end
$var wire 3 ! count [2:0] $end
$var reg 1 " clk $end
$var reg 1 # reset $end
$var reg 1 $ ud $end
$scope module uut $end
$var wire 1 " clk $end
$var wire 1 # reset $end
$var wire 1 $ ud $end
$var reg 3 % count [2:0] $end
$upscope $end
$upscope $end
$enddefinitions $end
$comment Show the parameter values. $end
$dumpall
$end
#0
$dumpvars
b0 %
1$
1#
0"
b0 !
$end
#5000
1"
#10000
0"
0#
#15000
b1 !
b1 %
1"
#20000
0"
#25000
b10 !
b10 %
1"
#30000
0"
#35000
b11 !
b11 %
1"
#40000
0"
#45000
b100 !
b100 %
1"
#50000
0"
#55000
b101 !
b101 %
1"
#60000
0"
0$
#65000
b100 !
b100 %
1"
#70000
0"
#75000
b11 !
b11 %
1"
#80000
0"
#85000
b10 !
b10 %
1"
#90000
0"
#95000
b1 !
b1 %
1"
#100000
0"
#105000
b0 !
b0 %
1"
#110000
0"
1#
#115000
1"
#120000
0"
1$
0#
#125000
b1 !
b1 %
1"
#130000
0"
#135000
b10 !
b10 %
1"
#140000
0"
#145000
b11 !
b11 %
1"
#150000
0"
#155000
b100 !
b100 %
1"
#160000
0"
#165000
b101 !
b101 %
1"
